[{
    "name": "doc1",
    "title": "INSTALLATION MANUAL",
    "thumb": "pdf",
    "url": "help/getfile?lang=eng&file=Climate Station Installation manual V1.3.2.pdf",
    "type": "USER DOCUMENTATION",
    "uploaded": "February, 2025"
},{
    "name": "doc2",
    "title": "PRODUCT REPORT",
    "thumb": "pdf",
    "url": "help/getfile?lang=eng&file=Climate Station Product Report V1.3.1.pdf",
    "type": "USER DOCUMENTATION",
    "uploaded": "September, 2024"
},{
    "name": "doc3",
    "title": "USER MANUAL",
    "thumb": "pdf",
    "url": "help/getfile?lang=eng&file=Climate Station User Manual V1.3.0.pdf",
    "type": "USER DOCUMENTATION",
    "uploaded": "June, 2024"
},{
    "name": "doc4",
    "title": "DATA PROVIDER REGISTRATION",
    "thumb": "pdf",
    "url": "help/getfile?lang=eng&file=Climate Station Data Provider manual V1.3.1.pdf",
    "type": "USER DOCUMENTATION",
    "uploaded": "September, 2024"
}]
